{"swagger":"2.0","info":{"title":"Swagger Json","description":"This is a generated swagger json for your sails project","termsOfService":"","contact":{"name":"Nirav Adatiya","url":"https://github.com/logisticinfotech","email":"nirav@logisticinfotech.com"},"license":{"name":"Apache 2.0","url":"http://www.apache.org/licenses/LICENSE-2.0.html"},"version":"1.0.0"},"host":"localhost:1337","basePath":"/","schemes":["http","https"],"externalDocs":{"url":"http://www.logisticinfotech.com"},"parameters":{"WhereQueryParam":{"in":"query","name":"where","required":false,"type":"string","description":"This follows the standard from http://sailsjs.com/documentation/reference/blueprint-api/find-where"},"LimitQueryParam":{"in":"query","name":"limit","required":false,"type":"integer","description":"The maximum number of records to send back (useful for pagination). Defaults to undefined"},"SkipQueryParam":{"in":"query","name":"skip","required":false,"type":"integer","description":"The number of records to skip (useful for pagination)."},"SortQueryParam":{"in":"query","name":"sort","required":false,"type":"string","description":"The sort order. By default, returned records are sorted by primary key value in ascending order. e.g. ?sort=lastName%20ASC"},"PopulateQueryParam":{"in":"query","name":"populate","required":false,"type":"string","description":"check for better understanding -> http://sailsjs.com/documentation/reference/blueprint-api/find-where"},"PageQueryParam":{"in":"query","name":"page","required":false,"type":"integer","description":"This helps with pagination and when the limit is known"},"SelectQueryParam":{"in":"query","name":"select","required":false,"type":"string","description":"This helps with what to return for the user and its \",\" delimited"},"TokenHeaderParam":{"in":"header","name":"token","required":false,"type":"string","description":"Incase we want to send header information along our request"},"IDPathParam":{"in":"path","name":"id","required":true,"type":"string","description":"This is to identify a particular object out"},"PerPageQueryParam":{"in":"query","name":"perPage","required":false,"type":"integer","description":"This helps with pagination and when the limit is known for pagify"}},"paths":{"/":{"get":{"tags":["/"],"summary":"","consumes":["application/json"],"produces":["application/json"],"responses":{"200":{"description":"The requested resource"},"404":{"description":"Resource not found"},"500":{"description":"Internal server error"}},"security":[{"Authorization":[]}]}},"/welcome/{unused?}":{"get":{"tags":["Welcome"],"summary":"","consumes":["application/json"],"produces":["application/json"],"responses":{"200":{"description":"The requested resource"},"404":{"description":"Resource not found"},"500":{"description":"Internal server error"}},"security":[{"Authorization":[]}]}},"/faq":{"get":{"tags":["Faq"],"summary":"","consumes":["application/json"],"produces":["application/json"],"responses":{"200":{"description":"The requested resource"},"404":{"description":"Resource not found"},"500":{"description":"Internal server error"}},"security":[{"Authorization":[]}]}},"/legal/terms":{"get":{"tags":["Legal"],"summary":"","consumes":["application/json"],"produces":["application/json"],"responses":{"200":{"description":"The requested resource"},"404":{"description":"Resource not found"},"500":{"description":"Internal server error"}},"security":[{"Authorization":[]}]}},"/legal/privacy":{"get":{"tags":["Legal"],"summary":"","consumes":["application/json"],"produces":["application/json"],"responses":{"200":{"description":"The requested resource"},"404":{"description":"Resource not found"},"500":{"description":"Internal server error"}},"security":[{"Authorization":[]}]}},"/contact":{"get":{"tags":["Contact"],"summary":"","consumes":["application/json"],"produces":["application/json"],"responses":{"200":{"description":"The requested resource"},"404":{"description":"Resource not found"},"500":{"description":"Internal server error"}},"security":[{"Authorization":[]}]}},"/signup":{"get":{"tags":["Signup"],"summary":"","consumes":["application/json"],"produces":["application/json"],"responses":{"200":{"description":"The requested resource"},"404":{"description":"Resource not found"},"500":{"description":"Internal server error"}},"security":[{"Authorization":[]}]}},"/email/confirm":{"get":{"tags":["Email"],"summary":"","consumes":["application/json"],"produces":["application/json"],"responses":{"200":{"description":"The requested resource"},"404":{"description":"Resource not found"},"500":{"description":"Internal server error"}},"security":[{"Authorization":[]}],"parameters":[{"in":"query","name":"token","required":false,"type":"","description":"The confirmation token from the email."}]}},"/email/confirmed":{"get":{"tags":["Email"],"summary":"","consumes":["application/json"],"produces":["application/json"],"responses":{"200":{"description":"The requested resource"},"404":{"description":"Resource not found"},"500":{"description":"Internal server error"}},"security":[{"Authorization":[]}]}},"/login":{"get":{"tags":["Login"],"summary":"","consumes":["application/json"],"produces":["application/json"],"responses":{"200":{"description":"The requested resource"},"404":{"description":"Resource not found"},"500":{"description":"Internal server error"}},"security":[{"Authorization":[]}]}},"/password/forgot":{"get":{"tags":["Password"],"summary":"","consumes":["application/json"],"produces":["application/json"],"responses":{"200":{"description":"The requested resource"},"404":{"description":"Resource not found"},"500":{"description":"Internal server error"}},"security":[{"Authorization":[]}]}},"/password/new":{"get":{"tags":["Password"],"summary":"","consumes":["application/json"],"produces":["application/json"],"responses":{"200":{"description":"The requested resource"},"404":{"description":"Resource not found"},"500":{"description":"Internal server error"}},"security":[{"Authorization":[]}],"parameters":[{"in":"query","name":"token","required":false,"type":"","description":"The password reset token from the email."}]}},"/account":{"get":{"tags":["Account"],"summary":"","consumes":["application/json"],"produces":["application/json"],"responses":{"200":{"description":"The requested resource"},"404":{"description":"Resource not found"},"500":{"description":"Internal server error"}},"security":[{"Authorization":[]}]}},"/account/password":{"get":{"tags":["Account"],"summary":"","consumes":["application/json"],"produces":["application/json"],"responses":{"200":{"description":"The requested resource"},"404":{"description":"Resource not found"},"500":{"description":"Internal server error"}},"security":[{"Authorization":[]}]}},"/account/profile":{"get":{"tags":["Account"],"summary":"","consumes":["application/json"],"produces":["application/json"],"responses":{"200":{"description":"The requested resource"},"404":{"description":"Resource not found"},"500":{"description":"Internal server error"}},"security":[{"Authorization":[]}]}},"/terms":{},"/logout":{},"/api/v1/account/logout":{"get":{"tags":["Account"],"summary":"","consumes":["application/json"],"produces":["application/json"],"responses":{"200":{"description":"The requested resource"},"404":{"description":"Resource not found"},"500":{"description":"Internal server error"}},"security":[{"Authorization":[]}]}},"  /api/v1/account/update-password":{"put":{"tags":["Account"],"summary":"","consumes":["application/json"],"produces":["application/json"],"responses":{"200":{"description":"The requested resource"},"404":{"description":"Resource not found"},"500":{"description":"Internal server error"}},"security":[{"Authorization":[]}],"parameters":[{"name":"body","in":"body","required":true,"description":"An object defining our schema for this request","schema":{"properties":{"password":{"description":"The new, unencrypted password."}},"required":["password"]}}]}},"  /api/v1/account/update-profile":{"put":{"tags":["Account"],"summary":"","consumes":["application/json"],"produces":["application/json"],"responses":{"200":{"description":"The requested resource"},"404":{"description":"Resource not found"},"500":{"description":"Internal server error"}},"security":[{"Authorization":[]}],"parameters":[{"name":"body","in":"body","required":true,"description":"An object defining our schema for this request","schema":{"properties":{"fullName":{"type":"string"},"emailAddress":{"type":"string"}},"required":[]}}]}},"  /api/v1/account/update-billing-card":{"put":{"tags":["Account"],"summary":"","consumes":["application/json"],"produces":["application/json"],"responses":{"200":{"description":"The requested resource"},"404":{"description":"Resource not found"},"500":{"description":"Internal server error"}},"security":[{"Authorization":[]}],"parameters":[{"name":"body","in":"body","required":true,"description":"An object defining our schema for this request","schema":{"properties":{"stripeToken":{"type":"string","description":"The single-use Stripe Checkout token identifier representing the user's payment source (i.e. credit card.)"},"billingCardLast4":{"type":"string","description":"Omit if removing card info."},"billingCardBrand":{"type":"string","description":"Omit if removing card info."},"billingCardExpMonth":{"type":"string","description":"Omit if removing card info."},"billingCardExpYear":{"type":"string","description":"Omit if removing card info."}},"required":[]}}]}},"  /api/v1/entrance/login":{"put":{"tags":["Entrance"],"summary":"","consumes":["application/json"],"produces":["application/json"],"responses":{"200":{"description":"The requested resource"},"404":{"description":"Resource not found"},"500":{"description":"Internal server error"}},"security":[{"Authorization":[]}],"parameters":[{"name":"body","in":"body","required":true,"description":"An object defining our schema for this request","schema":{"properties":{"emailAddress":{"type":"string","description":"The email to try in this attempt, e.g. \"irl@example.com\"."},"password":{"type":"string","description":"The unencrypted password to try in this attempt, e.g. \"passwordlol\"."},"rememberMe":{"type":"boolean","description":"Whether to extend the lifetime of the user's session."}},"required":["emailAddress","password"]}}]}}," /api/v1/entrance/signup":{"post":{"tags":["Entrance"],"summary":"","consumes":["application/json"],"produces":["application/json"],"responses":{"200":{"description":"The requested resource"},"404":{"description":"Resource not found"},"500":{"description":"Internal server error"}},"security":[{"Authorization":[]}],"parameters":[{"name":"body","in":"body","required":true,"description":"An object defining our schema for this request","schema":{"properties":{"emailAddress":{"type":"string","description":"The email address for the new account, e.g. m@example.com."},"password":{"type":"string","description":"The unencrypted password to use for the new account."},"fullName":{"type":"string","description":"The user's full name."}},"required":["emailAddress","password","fullName"]}}]}}," /api/v1/entrance/send-password-recovery-email":{"post":{"tags":["Entrance"],"summary":"","consumes":["application/json"],"produces":["application/json"],"responses":{"200":{"description":"The requested resource"},"404":{"description":"Resource not found"},"500":{"description":"Internal server error"}},"security":[{"Authorization":[]}],"parameters":[{"name":"body","in":"body","required":true,"description":"An object defining our schema for this request","schema":{"properties":{"emailAddress":{"type":"string","description":"The email address of the alleged user who wants to recover their password."}},"required":["emailAddress"]}}]}}," /api/v1/entrance/update-password-and-login":{"post":{"tags":["Entrance"],"summary":"","consumes":["application/json"],"produces":["application/json"],"responses":{"200":{"description":"The requested resource"},"404":{"description":"Resource not found"},"500":{"description":"Internal server error"}},"security":[{"Authorization":[]}],"parameters":[{"name":"body","in":"body","required":true,"description":"An object defining our schema for this request","schema":{"properties":{"password":{"description":"The new, unencrypted password."},"token":{"description":"The password token that was generated by the `sendPasswordRecoveryEmail` endpoint."}},"required":["password","token"]}}]}}," /api/v1/deliver-contact-form-message":{"post":{"tags":["Deliver-contact-form-message"],"summary":"","consumes":["application/json"],"produces":["application/json"],"responses":{"200":{"description":"The requested resource"},"404":{"description":"Resource not found"},"500":{"description":"Internal server error"}},"security":[{"Authorization":[]}],"parameters":[{"name":"body","in":"body","required":true,"description":"An object defining our schema for this request","schema":{"properties":{"emailAddress":{"type":"string","description":"A return email address where we can respond."},"topic":{"type":"string","description":"The topic from the contact form."},"fullName":{"type":"string","description":"The full name of the human sending this message."},"message":{"type":"string","description":"The custom message, in plain text."}},"required":["emailAddress","topic","fullName","message"]}}]}}," /api/v1/observe-my-session":{"post":{"tags":["Observe-my-session"],"summary":"","consumes":["application/json"],"produces":["application/json"],"responses":{"200":{"description":"The requested resource"},"404":{"description":"Resource not found"},"500":{"description":"Internal server error"}},"security":[{"Authorization":[]}],"parameters":[{"name":"body","in":"body","required":true,"description":"An object defining our schema for this request","schema":{"properties":{},"required":[]}}]}}},"definitions":{"user":{"properties":{"createdAt":{"type":"number"},"updatedAt":{"type":"number"},"id":{"type":"number","uniqueItems":true},"emailAddress":{"type":"string","format":"email","maxLength":200,"example":"mary.sue@example.com","uniqueItems":true},"emailStatus":{"type":"string","description":"The confirmation status of the user's email address.","default":"confirmed","enum":["unconfirmed","change-requested","confirmed"]},"emailChangeCandidate":{"type":"string","description":"A still-unconfirmed email address that this user wants to change to (if relevant).","format":"email"},"password":{"type":"string","description":"Securely hashed representation of the user's login password.","example":"2$28a8eabna301089103-13948134nad"},"fullName":{"type":"string","description":"Full representation of the user's name.","maxLength":120,"example":"Mary Sue van der McHenst"},"isSuperAdmin":{"type":"boolean","description":"Whether this user is a \"super admin\" with extra permissions, etc."},"passwordResetToken":{"type":"string","description":"A unique token used to verify the user's identity when recovering a password.  Expires after 1 use, or after a set amount of time has elapsed."},"passwordResetTokenExpiresAt":{"type":"number","description":"A JS timestamp (epoch ms) representing the moment when this user's `passwordResetToken` will expire (or 0 if the user currently has no such token).","example":1502844074211},"emailProofToken":{"type":"string","description":"A pseudorandom, probabilistically-unique token for use in our account verification emails."},"emailProofTokenExpiresAt":{"type":"number","description":"A JS timestamp (epoch ms) representing the moment when this user's `emailProofToken` will expire (or 0 if the user currently has no such token).","example":1502844074211},"stripeCustomerId":{"type":"string","description":"The id of the customer entry in Stripe associated with this user (or empty string if this user is not linked to a Stripe customer -- e.g. if billing features are not enabled)."},"hasBillingCard":{"type":"boolean","description":"Whether this user has a default billing card hooked up as their payment method."},"billingCardBrand":{"type":"string","description":"The brand of this user's default billing card (or empty string if no billing card is set up).","example":"Visa"},"billingCardLast4":{"type":"string","description":"The last four digits of the card number for this user's default billing card (or empty string if no billing card is set up).","example":"4242"},"billingCardExpMonth":{"type":"string","description":"The two-digit expiration month from this user's default billing card, formatted as MM (or empty string if no billing card is set up).","example":"08"},"billingCardExpYear":{"type":"string","description":"The four-digit expiration year from this user's default billing card, formatted as YYYY (or empty string if no credit card is set up).","example":"2023"},"tosAcceptedByIp":{"type":"string","description":"The IP (ipv4) address of the request that accepted the terms of service."},"lastSeenAt":{"type":"number","description":"A JS timestamp (epoch ms) representing the moment at which this user most recently interacted with the backend while logged in (or 0 if they have not interacted with the backend at all yet).","example":1502844074211}},"required":["emailAddress","password","fullName"]},"archive":{"properties":{"id":{"type":"number","uniqueItems":true},"createdAt":{"type":"number"},"fromModel":{"type":"string"},"originalRecord":{"type":"json"},"originalRecordId":{"type":"json"}},"required":["fromModel","originalRecord"]}},"securityDefinitions":{"Authorization":{"type":"apiKey","description":"user JWT Auth Token","name":"Authorization","in":"header","flow":"password"}}}